snipeitpythonapi/Accessories.py
snipeitpythonapi/Assets.py
snipeitpythonapi/AssetsMaintenances.py
snipeitpythonapi/Categories.py
snipeitpythonapi/Company.py
snipeitpythonapi/Components.py
snipeitpythonapi/Consumables.py
snipeitpythonapi/DataUtil.py
snipeitpythonapi/Fieldsets.py
snipeitpythonapi/Licenses.py
snipeitpythonapi/Locations.py
snipeitpythonapi/Maintenances.py
snipeitpythonapi/Manufacturers.py
snipeitpythonapi/Models.py
snipeitpythonapi/StatusLabels.py
snipeitpythonapi/Users.py
snipeitpythonapi/__init__.py
snipeitpythonapi-1.0.0.dist-info/METADATA
snipeitpythonapi-1.0.0.dist-info/WHEEL
snipeitpythonapi-1.0.0.dist-info/top_level.txt
snipeitpythonapi-1.0.0.dist-info/zip-safe
snipeitpythonapi-1.0.0.dist-info/RECORD
