Metadata-Version: 2.1
Name: snipeitpythonapi
Version: 1.0.0
Summary: Python library to access the Snipe-IT API
Home-page: https://github.com/Honoo/SnipeIT-PythonAPI
Author: Su Gi Chandran
License: MIT
Requires-Python: >=3.6
Requires-Dist: requests
Requires-Dist: simplejson
